{
    "Dépenses Ressources Humaines": [
        {
            "Crédit": 0
        },
        {
            "Débit": 0
        }
    ],
    "Achat carburant": [
        {
            "Crédit": 29659
        },
        {
            "Débit": 0
        }
    ],
    "Dépenses Domaine Skiable": [
        {
            "Crédit": 9900792
        },
        {
            "Débit": 0
        }
    ],
    "Construction de locaux": [
        {
            "Crédit": 0
        },
        {
            "Débit": 0
        }
    ],
    "Remboursements anticipés": [
        {
            "Crédit": 7230000
        },
        {
            "Débit": 0
        }
    ],
    "Achat de matériel": [
        {
            "Crédit": 0
        },
        {
            "Débit": 0
        }
    ],
    "Vente de matériel": [
        {
            "Crédit": 0
        },
        {
            "Débit": 0
        }
    ],
    "CA transports": [
        {
            "Crédit": 0
        },
        {
            "Débit": 377287
        }
    ],
    "CA domaine skiable": [
        {
            "Crédit": 0
        },
        {
            "Débit": 10931902
        }
    ],
    "CA hôtellerie": [
        {
            "Crédit": 0
        },
        {
            "Débit": 1764054
        }
    ],
    "CA restaurants": [
        {
            "Crédit": 0
        },
        {
            "Débit": 134762
        }
    ],
    "CA parkings": [
        {
            "Crédit": 0
        },
        {
            "Débit": 426033
        }
    ],
    "Dépenses & revenus location": [
        {
            "Crédit": 0
        },
        {
            "Débit": 0
        }
    ],
    "Revenus publicitaires": [
        {
            "Crédit": 0
        },
        {
            "Débit": 54000
        }
    ],
    "Maintenance des remontées mécaniques": [
        {
            "Crédit": 0
        },
        {
            "Débit": 0
        }
    ],
    "Maintenance des dameuses": [
        {
            "Crédit": 0
        },
        {
            "Débit": 0
        }
    ],
    "Concours & mini-jeu": [
        {
            "Crédit": 9000
        },
        {
            "Débit": 122000
        }
    ],
    "CA domaine ski de fond": [
        {
            "Crédit": 0
        },
        {
            "Débit": 87484
        }
    ],
    "Prévention des avalanches": [
        {
            "Crédit": 0
        },
        {
            "Débit": 0
        }
    ],
    "Subventions Conseil Général": [
        {
            "Crédit": 0
        },
        {
            "Débit": 220000
        }
    ],
    "Subventions de l'Etat": [
        {
            "Crédit": 0
        },
        {
            "Débit": 0
        }
    ],
    "TOTAL": [
        {
            "Crédit": 17169451
        },
        {
            "Débit": 14117522
        }
    ]
}