{
    "Dépenses Ressources Humaines": [
        {
            "Crédit": 0
        },
        {
            "Débit": 0
        }
    ],
    "Achat carburant": [
        {
            "Crédit": 29659
        },
        {
            "Débit": 0
        }
    ],
    "Dépenses Domaine Skiable": [
        {
            "Crédit": 9900792
        },
        {
            "Débit": 0
        }
    ],
    "Construction de locaux": [
        {
            "Crédit": 0
        },
        {
            "Débit": 0
        }
    ],
    "Remboursements anticipés": [
        {
            "Crédit": 7230000
        },
        {
            "Débit": 0
        }
    ],
    "Achat de matériel": [
        {
            "Crédit": 0
        },
        {
            "Débit": 0
        }
    ],
    "Vente de matériel": [
        {
            "Crédit": 0
        },
        {
            "Débit": 0
        }
    ],
    "CA transports": [
        {
            "Crédit": 0
        },
        {
            "Débit": 392464
        }
    ],
    "CA domaine skiable": [
        {
            "Crédit": 0
        },
        {
            "Débit": 11241387
        }
    ],
    "CA hôtellerie": [
        {
            "Crédit": 0
        },
        {
            "Débit": 1831310
        }
    ],
    "CA restaurants": [
        {
            "Crédit": 0
        },
        {
            "Débit": 140455
        }
    ],
    "CA parkings": [
        {
            "Crédit": 0
        },
        {
            "Débit": 442633
        }
    ],
    "Dépenses & revenus location": [
        {
            "Crédit": 0
        },
        {
            "Débit": 0
        }
    ],
    "Revenus publicitaires": [
        {
            "Crédit": 0
        },
        {
            "Débit": 54000
        }
    ],
    "Maintenance des remontées mécaniques": [
        {
            "Crédit": 0
        },
        {
            "Débit": 0
        }
    ],
    "Maintenance des dameuses": [
        {
            "Crédit": 0
        },
        {
            "Débit": 0
        }
    ],
    "Concours & mini-jeu": [
        {
            "Crédit": 10000
        },
        {
            "Débit": 132000
        }
    ],
    "CA domaine ski de fond": [
        {
            "Crédit": 0
        },
        {
            "Débit": 91152
        }
    ],
    "Prévention des avalanches": [
        {
            "Crédit": 0
        },
        {
            "Débit": 0
        }
    ],
    "Subventions Conseil Général": [
        {
            "Crédit": 0
        },
        {
            "Débit": 220000
        }
    ],
    "Subventions de l'Etat": [
        {
            "Crédit": 0
        },
        {
            "Débit": 0
        }
    ],
    "TOTAL": [
        {
            "Crédit": 17170451
        },
        {
            "Débit": 14545401
        }
    ]
}