{
    "Dépenses Ressources Humaines": [
        {
            "Crédit": 0
        },
        {
            "Débit": 0
        }
    ],
    "Achat carburant": [
        {
            "Crédit": 39203
        },
        {
            "Débit": 0
        }
    ],
    "Dépenses Domaine Skiable": [
        {
            "Crédit": 19444203
        },
        {
            "Débit": 0
        }
    ],
    "Construction de locaux": [
        {
            "Crédit": 0
        },
        {
            "Débit": 0
        }
    ],
    "Remboursements anticipés": [
        {
            "Crédit": 0
        },
        {
            "Débit": 0
        }
    ],
    "Achat de matériel": [
        {
            "Crédit": 3940000
        },
        {
            "Débit": 0
        }
    ],
    "Vente de matériel": [
        {
            "Crédit": 0
        },
        {
            "Débit": 0
        }
    ],
    "CA transports": [
        {
            "Crédit": 0
        },
        {
            "Débit": 473026
        }
    ],
    "CA domaine skiable": [
        {
            "Crédit": 0
        },
        {
            "Débit": 10604963
        }
    ],
    "CA hôtellerie": [
        {
            "Crédit": 0
        },
        {
            "Débit": 1629435
        }
    ],
    "CA restaurants": [
        {
            "Crédit": 0
        },
        {
            "Débit": 278945
        }
    ],
    "CA parkings": [
        {
            "Crédit": 0
        },
        {
            "Débit": 400980
        }
    ],
    "Dépenses & revenus location": [
        {
            "Crédit": 0
        },
        {
            "Débit": 0
        }
    ],
    "Revenus publicitaires": [
        {
            "Crédit": 0
        },
        {
            "Débit": 0
        }
    ],
    "Maintenance des remontées mécaniques": [
        {
            "Crédit": 0
        },
        {
            "Débit": 0
        }
    ],
    "Maintenance des dameuses": [
        {
            "Crédit": 0
        },
        {
            "Débit": 0
        }
    ],
    "Concours & mini-jeu": [
        {
            "Crédit": 8000
        },
        {
            "Débit": 110000
        }
    ],
    "CA domaine ski de fond": [
        {
            "Crédit": 0
        },
        {
            "Débit": 401325
        }
    ],
    "Prévention des avalanches": [
        {
            "Crédit": 1680
        },
        {
            "Débit": 0
        }
    ],
    "Subventions Conseil Général": [
        {
            "Crédit": 0
        },
        {
            "Débit": 0
        }
    ],
    "Subventions de l'Etat": [
        {
            "Crédit": 0
        },
        {
            "Débit": 0
        }
    ],
    "TOTAL": [
        {
            "Crédit": 23433086
        },
        {
            "Débit": 13898674
        }
    ]
}